fastpluggy_plugin/ui_tools/__init__.py
fastpluggy_plugin/ui_tools/html_render.py
fastpluggy_plugin/ui_tools/image_tools.py
fastpluggy_plugin/ui_tools/localization.py
fastpluggy_plugin/ui_tools/plugin.py
fastpluggy_plugin/ui_tools/template_tools.py
fastpluggy_plugin/ui_tools/extra_widget/__init__.py
fastpluggy_plugin/ui_tools/extra_widget/display/__init__.py
fastpluggy_plugin/ui_tools/extra_widget/display/alert.py
fastpluggy_plugin/ui_tools/extra_widget/display/card.py
fastpluggy_plugin/ui_tools/extra_widget/display/code.py
fastpluggy_plugin/ui_tools/extra_widget/display/progress.py
fastpluggy_plugin/ui_tools/extra_widget/display/stats.py
fastpluggy_plugin/ui_tools/extra_widget/layout/__init__.py
fastpluggy_plugin/ui_tools/extra_widget/layout/grid.py
fastpluggy_plugin/ui_tools/static/script.js
fastpluggy_plugin/ui_tools/static/style.css
fastpluggy_plugin/ui_tools/templates/mime.html.j2
fastpluggy_plugin/ui_tools/templates/extra_widget/__init__.py
fastpluggy_plugin/ui_tools/templates/extra_widget/display/alert.html.j2
fastpluggy_plugin/ui_tools/templates/extra_widget/display/card.html.j2
fastpluggy_plugin/ui_tools/templates/extra_widget/display/code.html.j2
fastpluggy_plugin/ui_tools/templates/extra_widget/display/progress.html.j2
fastpluggy_plugin/ui_tools/templates/extra_widget/display/stats.html.j2
fastpluggy_plugin/ui_tools/templates/extra_widget/display/status.html.j2
fastpluggy_plugin/ui_tools/templates/extra_widget/layout/grid.html.j2
fastpluggy_ui_tools-0.0.8.dist-info/METADATA
fastpluggy_ui_tools-0.0.8.dist-info/WHEEL
fastpluggy_ui_tools-0.0.8.dist-info/entry_points.txt
fastpluggy_ui_tools-0.0.8.dist-info/top_level.txt
fastpluggy_ui_tools-0.0.8.dist-info/RECORD
