Metadata-Version: 2.4
Name: fastpluggy-ui-tools
Version: 0.0.8
Summary: UI Tools plugin for Fastpluggy
Author: FastPluggy Team
Requires-Python: >=3.10
Requires-Dist: jinja2
Requires-Dist: babel
Requires-Dist: Pillow
